LICENSE
README.md
randprox.py
setup.py
randprox.egg-info/PKG-INFO
randprox.egg-info/SOURCES.txt
randprox.egg-info/dependency_links.txt
randprox.egg-info/top_level.txt