Metadata-Version: 2.1
Name: randprox
Version: 1.5
Summary: Get Random Proxy
Home-page: https://github.com/kattstof
Download-URL: https://github.com/kattstof/RandProx
Author: KattStof
Author-email: Kattstof@autistici.org
License: MIT
Keywords: proxy
Classifier: Programming Language :: Python :: 3
Classifier: Programming Language :: Python :: 3
Classifier: Programming Language :: Python :: 3
Requires: random
Requires: requests
License-File: LICENSE
